calculator/__init__.py
calculator/calculator.py
calculator_cz/__init__.py
calculator_cz/calculator_cz.py
calculator_cz-0.2.0.dist-info/LICENSE.txt
calculator_cz-0.2.0.dist-info/METADATA
calculator_cz-0.2.0.dist-info/WHEEL
calculator_cz-0.2.0.dist-info/top_level.txt
calculator_cz-0.2.0.dist-info/RECORD
